[

 { "proc":"BRISC" , "zone":"BRISC-KERNEL", "zone_phase":"begin", "sx":1 , "sy":1 , "timestamp" : 4350117285162 }
,{ "proc":"BRISC", "noc":"NOC_1", "vc":-1, "sx":1 ,  "sy":1 ,  "dx":1 ,  "dy":1 ,  "num_bytes":4096  ,  "type":"READ"                , "timestamp":4350117285352   , "kernel_start_delta":190    }
,{ "proc":"BRISC", "noc":"NOC_1", "vc":-1, "sx":1 ,  "sy":1 ,  "dx":1 ,  "dy":1 ,  "num_bytes":4096  ,  "type":"READ"                , "timestamp":4350117285504   , "kernel_start_delta":342    }
,{ "proc":"BRISC", "noc":"NOC_1", "vc":-1, "sx":1 ,  "sy":1 ,  "dx":-1,  "dy":-1,  "num_bytes":0     ,  "type":"READ_BARRIER_START"  , "timestamp":4350117285619   , "kernel_start_delta":457    }
,{ "proc":"BRISC", "noc":"NOC_1", "vc":-1, "sx":1 ,  "sy":1 ,  "dx":-1,  "dy":-1,  "num_bytes":0     ,  "type":"READ_BARRIER_END"    , "timestamp":4350117286395   , "kernel_start_delta":1233   }

,{ "proc":"NCRISC", "zone":"NCRISC-KERNEL", "zone_phase":"begin", "sx":1 , "sy":1 , "timestamp" : 4350117285320 }
,{ "proc":"NCRISC", "noc":"NOC_0", "vc":-1, "sx":1 ,  "sy":1 ,  "dx":1 ,  "dy":1 ,  "num_bytes":4096  ,  "type":"READ"                , "timestamp":4350117285546   , "kernel_start_delta":226    }
,{ "proc":"NCRISC", "noc":"NOC_0", "vc":-1, "sx":1 ,  "sy":1 ,  "dx":1 ,  "dy":1 ,  "num_bytes":4096  ,  "type":"READ"                , "timestamp":4350117285687   , "kernel_start_delta":367    }
,{ "proc":"NCRISC", "noc":"NOC_0", "vc":-1, "sx":1 ,  "sy":1 ,  "dx":-1,  "dy":-1,  "num_bytes":0     ,  "type":"READ_BARRIER_START"  , "timestamp":4350117285815   , "kernel_start_delta":495    }
,{ "proc":"NCRISC", "noc":"NOC_0", "vc":-1, "sx":1 ,  "sy":1 ,  "dx":-1,  "dy":-1,  "num_bytes":0     ,  "type":"READ_BARRIER_END"    , "timestamp":4350117286394   , "kernel_start_delta":1074   }

,{ "proc":"BRISC" , "zone":"BRISC-KERNEL", "zone_phase":"begin", "sx":1 , "sy":2 , "timestamp" : 4350117285197 }
,{ "proc":"BRISC", "noc":"NOC_1", "vc":-1, "sx":1 ,  "sy":2 ,  "dx":1 ,  "dy":1 ,  "num_bytes":4096  ,  "type":"READ"                , "timestamp":4350117285387   , "kernel_start_delta":190    }
,{ "proc":"BRISC", "noc":"NOC_1", "vc":-1, "sx":1 ,  "sy":2 ,  "dx":1 ,  "dy":1 ,  "num_bytes":4096  ,  "type":"READ"                , "timestamp":4350117285540   , "kernel_start_delta":343    }
,{ "proc":"BRISC", "noc":"NOC_1", "vc":-1, "sx":1 ,  "sy":2 ,  "dx":-1,  "dy":-1,  "num_bytes":0     ,  "type":"READ_BARRIER_START"  , "timestamp":4350117285657   , "kernel_start_delta":460    }
,{ "proc":"BRISC", "noc":"NOC_1", "vc":-1, "sx":1 ,  "sy":2 ,  "dx":-1,  "dy":-1,  "num_bytes":0     ,  "type":"READ_BARRIER_END"    , "timestamp":4350117287823   , "kernel_start_delta":2626   }

,{ "proc":"NCRISC", "zone":"NCRISC-KERNEL", "zone_phase":"begin", "sx":1 , "sy":2 , "timestamp" : 4350117285343 }
,{ "proc":"NCRISC", "noc":"NOC_0", "vc":-1, "sx":1 ,  "sy":2 ,  "dx":1 ,  "dy":1 ,  "num_bytes":4096  ,  "type":"READ"                , "timestamp":4350117285566   , "kernel_start_delta":223    }
,{ "proc":"NCRISC", "noc":"NOC_0", "vc":-1, "sx":1 ,  "sy":2 ,  "dx":1 ,  "dy":1 ,  "num_bytes":4096  ,  "type":"READ"                , "timestamp":4350117285708   , "kernel_start_delta":365    }
,{ "proc":"NCRISC", "noc":"NOC_0", "vc":-1, "sx":1 ,  "sy":2 ,  "dx":-1,  "dy":-1,  "num_bytes":0     ,  "type":"READ_BARRIER_START"  , "timestamp":4350117285835   , "kernel_start_delta":492    }
,{ "proc":"NCRISC", "noc":"NOC_0", "vc":-1, "sx":1 ,  "sy":2 ,  "dx":-1,  "dy":-1,  "num_bytes":0     ,  "type":"READ_BARRIER_END"    , "timestamp":4350117287983   , "kernel_start_delta":2640   }

,{ "proc":"BRISC" , "zone":"BRISC-KERNEL", "zone_phase":"begin", "sx":1 , "sy":3 , "timestamp" : 4350117285178 }
,{ "proc":"BRISC", "noc":"NOC_1", "vc":-1, "sx":1 ,  "sy":3 ,  "dx":1 ,  "dy":1 ,  "num_bytes":4096  ,  "type":"READ"                , "timestamp":4350117285368   , "kernel_start_delta":190    }
,{ "proc":"BRISC", "noc":"NOC_1", "vc":-1, "sx":1 ,  "sy":3 ,  "dx":1 ,  "dy":1 ,  "num_bytes":4096  ,  "type":"READ"                , "timestamp":4350117285519   , "kernel_start_delta":341    }
,{ "proc":"BRISC", "noc":"NOC_1", "vc":-1, "sx":1 ,  "sy":3 ,  "dx":-1,  "dy":-1,  "num_bytes":0     ,  "type":"READ_BARRIER_START"  , "timestamp":4350117285636   , "kernel_start_delta":458    }
,{ "proc":"BRISC", "noc":"NOC_1", "vc":-1, "sx":1 ,  "sy":3 ,  "dx":-1,  "dy":-1,  "num_bytes":0     ,  "type":"READ_BARRIER_END"    , "timestamp":4350117287382   , "kernel_start_delta":2204   }

,{ "proc":"NCRISC", "zone":"NCRISC-KERNEL", "zone_phase":"begin", "sx":1 , "sy":3 , "timestamp" : 4350117285324 }
,{ "proc":"NCRISC", "noc":"NOC_0", "vc":-1, "sx":1 ,  "sy":3 ,  "dx":1 ,  "dy":1 ,  "num_bytes":4096  ,  "type":"READ"                , "timestamp":4350117285547   , "kernel_start_delta":223    }
,{ "proc":"NCRISC", "noc":"NOC_0", "vc":-1, "sx":1 ,  "sy":3 ,  "dx":1 ,  "dy":1 ,  "num_bytes":4096  ,  "type":"READ"                , "timestamp":4350117285689   , "kernel_start_delta":365    }
,{ "proc":"NCRISC", "noc":"NOC_0", "vc":-1, "sx":1 ,  "sy":3 ,  "dx":-1,  "dy":-1,  "num_bytes":0     ,  "type":"READ_BARRIER_START"  , "timestamp":4350117285811   , "kernel_start_delta":487    }
,{ "proc":"NCRISC", "noc":"NOC_0", "vc":-1, "sx":1 ,  "sy":3 ,  "dx":-1,  "dy":-1,  "num_bytes":0     ,  "type":"READ_BARRIER_END"    , "timestamp":4350117287849   , "kernel_start_delta":2525   }

,{ "proc":"BRISC" , "zone":"BRISC-KERNEL", "zone_phase":"begin", "sx":1 , "sy":4 , "timestamp" : 4350117285186 }
,{ "proc":"BRISC", "noc":"NOC_1", "vc":-1, "sx":1 ,  "sy":4 ,  "dx":1 ,  "dy":1 ,  "num_bytes":4096  ,  "type":"READ"                , "timestamp":4350117285376   , "kernel_start_delta":190    }
,{ "proc":"BRISC", "noc":"NOC_1", "vc":-1, "sx":1 ,  "sy":4 ,  "dx":1 ,  "dy":1 ,  "num_bytes":4096  ,  "type":"READ"                , "timestamp":4350117285529   , "kernel_start_delta":343    }
,{ "proc":"BRISC", "noc":"NOC_1", "vc":-1, "sx":1 ,  "sy":4 ,  "dx":-1,  "dy":-1,  "num_bytes":0     ,  "type":"READ_BARRIER_START"  , "timestamp":4350117285646   , "kernel_start_delta":460    }
,{ "proc":"BRISC", "noc":"NOC_1", "vc":-1, "sx":1 ,  "sy":4 ,  "dx":-1,  "dy":-1,  "num_bytes":0     ,  "type":"READ_BARRIER_END"    , "timestamp":4350117287960   , "kernel_start_delta":2774   }

,{ "proc":"NCRISC", "zone":"NCRISC-KERNEL", "zone_phase":"begin", "sx":1 , "sy":4 , "timestamp" : 4350117285332 }
,{ "proc":"NCRISC", "noc":"NOC_0", "vc":-1, "sx":1 ,  "sy":4 ,  "dx":1 ,  "dy":1 ,  "num_bytes":4096  ,  "type":"READ"                , "timestamp":4350117285555   , "kernel_start_delta":223    }
,{ "proc":"NCRISC", "noc":"NOC_0", "vc":-1, "sx":1 ,  "sy":4 ,  "dx":1 ,  "dy":1 ,  "num_bytes":4096  ,  "type":"READ"                , "timestamp":4350117285697   , "kernel_start_delta":365    }
,{ "proc":"NCRISC", "noc":"NOC_0", "vc":-1, "sx":1 ,  "sy":4 ,  "dx":-1,  "dy":-1,  "num_bytes":0     ,  "type":"READ_BARRIER_START"  , "timestamp":4350117285825   , "kernel_start_delta":493    }
,{ "proc":"NCRISC", "noc":"NOC_0", "vc":-1, "sx":1 ,  "sy":4 ,  "dx":-1,  "dy":-1,  "num_bytes":0     ,  "type":"READ_BARRIER_END"    , "timestamp":4350117287708   , "kernel_start_delta":2376   }

,{ "proc":"BRISC" , "zone":"BRISC-KERNEL", "zone_phase":"begin", "sx":1 , "sy":5 , "timestamp" : 4350117285149 }
,{ "proc":"BRISC", "noc":"NOC_1", "vc":-1, "sx":1 ,  "sy":5 ,  "dx":1 ,  "dy":1 ,  "num_bytes":4096  ,  "type":"READ"                , "timestamp":4350117285339   , "kernel_start_delta":190    }
,{ "proc":"BRISC", "noc":"NOC_1", "vc":-1, "sx":1 ,  "sy":5 ,  "dx":1 ,  "dy":1 ,  "num_bytes":4096  ,  "type":"READ"                , "timestamp":4350117285490   , "kernel_start_delta":341    }
,{ "proc":"BRISC", "noc":"NOC_1", "vc":-1, "sx":1 ,  "sy":5 ,  "dx":-1,  "dy":-1,  "num_bytes":0     ,  "type":"READ_BARRIER_START"  , "timestamp":4350117285607   , "kernel_start_delta":458    }
,{ "proc":"BRISC", "noc":"NOC_1", "vc":-1, "sx":1 ,  "sy":5 ,  "dx":-1,  "dy":-1,  "num_bytes":0     ,  "type":"READ_BARRIER_END"    , "timestamp":4350117287072   , "kernel_start_delta":1923   }

,{ "proc":"NCRISC", "zone":"NCRISC-KERNEL", "zone_phase":"begin", "sx":1 , "sy":5 , "timestamp" : 4350117285295 }
,{ "proc":"NCRISC", "noc":"NOC_0", "vc":-1, "sx":1 ,  "sy":5 ,  "dx":1 ,  "dy":1 ,  "num_bytes":4096  ,  "type":"READ"                , "timestamp":4350117285518   , "kernel_start_delta":223    }
,{ "proc":"NCRISC", "noc":"NOC_0", "vc":-1, "sx":1 ,  "sy":5 ,  "dx":1 ,  "dy":1 ,  "num_bytes":4096  ,  "type":"READ"                , "timestamp":4350117285660   , "kernel_start_delta":365    }
,{ "proc":"NCRISC", "noc":"NOC_0", "vc":-1, "sx":1 ,  "sy":5 ,  "dx":-1,  "dy":-1,  "num_bytes":0     ,  "type":"READ_BARRIER_START"  , "timestamp":4350117285785   , "kernel_start_delta":490    }
,{ "proc":"NCRISC", "noc":"NOC_0", "vc":-1, "sx":1 ,  "sy":5 ,  "dx":-1,  "dy":-1,  "num_bytes":0     ,  "type":"READ_BARRIER_END"    , "timestamp":4350117287574   , "kernel_start_delta":2279   }

,{ "proc":"BRISC" , "zone":"BRISC-KERNEL", "zone_phase":"begin", "sx":1 , "sy":7 , "timestamp" : 4350117285148 }
,{ "proc":"BRISC", "noc":"NOC_1", "vc":-1, "sx":1 ,  "sy":7 ,  "dx":1 ,  "dy":1 ,  "num_bytes":4096  ,  "type":"READ"                , "timestamp":4350117285338   , "kernel_start_delta":190    }
,{ "proc":"BRISC", "noc":"NOC_1", "vc":-1, "sx":1 ,  "sy":7 ,  "dx":1 ,  "dy":1 ,  "num_bytes":4096  ,  "type":"READ"                , "timestamp":4350117285489   , "kernel_start_delta":341    }
,{ "proc":"BRISC", "noc":"NOC_1", "vc":-1, "sx":1 ,  "sy":7 ,  "dx":-1,  "dy":-1,  "num_bytes":0     ,  "type":"READ_BARRIER_START"  , "timestamp":4350117285606   , "kernel_start_delta":458    }
,{ "proc":"BRISC", "noc":"NOC_1", "vc":-1, "sx":1 ,  "sy":7 ,  "dx":-1,  "dy":-1,  "num_bytes":0     ,  "type":"READ_BARRIER_END"    , "timestamp":4350117287496   , "kernel_start_delta":2348   }

,{ "proc":"NCRISC", "zone":"NCRISC-KERNEL", "zone_phase":"begin", "sx":1 , "sy":7 , "timestamp" : 4350117285294 }
,{ "proc":"NCRISC", "noc":"NOC_0", "vc":-1, "sx":1 ,  "sy":7 ,  "dx":1 ,  "dy":1 ,  "num_bytes":4096  ,  "type":"READ"                , "timestamp":4350117285517   , "kernel_start_delta":223    }
,{ "proc":"NCRISC", "noc":"NOC_0", "vc":-1, "sx":1 ,  "sy":7 ,  "dx":1 ,  "dy":1 ,  "num_bytes":4096  ,  "type":"READ"                , "timestamp":4350117285659   , "kernel_start_delta":365    }
,{ "proc":"NCRISC", "noc":"NOC_0", "vc":-1, "sx":1 ,  "sy":7 ,  "dx":-1,  "dy":-1,  "num_bytes":0     ,  "type":"READ_BARRIER_START"  , "timestamp":4350117285789   , "kernel_start_delta":495    }
,{ "proc":"NCRISC", "noc":"NOC_0", "vc":-1, "sx":1 ,  "sy":7 ,  "dx":-1,  "dy":-1,  "num_bytes":0     ,  "type":"READ_BARRIER_END"    , "timestamp":4350117287448   , "kernel_start_delta":2154   }

,{ "proc":"BRISC" , "zone":"BRISC-KERNEL", "zone_phase":"begin", "sx":1 , "sy":8 , "timestamp" : 4350117285142 }
,{ "proc":"BRISC", "noc":"NOC_1", "vc":-1, "sx":1 ,  "sy":8 ,  "dx":1 ,  "dy":1 ,  "num_bytes":4096  ,  "type":"READ"                , "timestamp":4350117285332   , "kernel_start_delta":190    }
,{ "proc":"BRISC", "noc":"NOC_1", "vc":-1, "sx":1 ,  "sy":8 ,  "dx":1 ,  "dy":1 ,  "num_bytes":4096  ,  "type":"READ"                , "timestamp":4350117285485   , "kernel_start_delta":343    }
,{ "proc":"BRISC", "noc":"NOC_1", "vc":-1, "sx":1 ,  "sy":8 ,  "dx":-1,  "dy":-1,  "num_bytes":0     ,  "type":"READ_BARRIER_START"  , "timestamp":4350117285602   , "kernel_start_delta":460    }
,{ "proc":"BRISC", "noc":"NOC_1", "vc":-1, "sx":1 ,  "sy":8 ,  "dx":-1,  "dy":-1,  "num_bytes":0     ,  "type":"READ_BARRIER_END"    , "timestamp":4350117287626   , "kernel_start_delta":2484   }

,{ "proc":"NCRISC", "zone":"NCRISC-KERNEL", "zone_phase":"begin", "sx":1 , "sy":8 , "timestamp" : 4350117285288 }
,{ "proc":"NCRISC", "noc":"NOC_0", "vc":-1, "sx":1 ,  "sy":8 ,  "dx":1 ,  "dy":1 ,  "num_bytes":4096  ,  "type":"READ"                , "timestamp":4350117285511   , "kernel_start_delta":223    }
,{ "proc":"NCRISC", "noc":"NOC_0", "vc":-1, "sx":1 ,  "sy":8 ,  "dx":1 ,  "dy":1 ,  "num_bytes":4096  ,  "type":"READ"                , "timestamp":4350117285653   , "kernel_start_delta":365    }
,{ "proc":"NCRISC", "noc":"NOC_0", "vc":-1, "sx":1 ,  "sy":8 ,  "dx":-1,  "dy":-1,  "num_bytes":0     ,  "type":"READ_BARRIER_START"  , "timestamp":4350117285778   , "kernel_start_delta":490    }
,{ "proc":"NCRISC", "noc":"NOC_0", "vc":-1, "sx":1 ,  "sy":8 ,  "dx":-1,  "dy":-1,  "num_bytes":0     ,  "type":"READ_BARRIER_END"    , "timestamp":4350117287317   , "kernel_start_delta":2029   }

,{ "proc":"BRISC" , "zone":"BRISC-KERNEL", "zone_phase":"begin", "sx":1 , "sy":9 , "timestamp" : 4350117285123 }
,{ "proc":"BRISC", "noc":"NOC_1", "vc":-1, "sx":1 ,  "sy":9 ,  "dx":1 ,  "dy":1 ,  "num_bytes":4096  ,  "type":"READ"                , "timestamp":4350117285313   , "kernel_start_delta":190    }
,{ "proc":"BRISC", "noc":"NOC_1", "vc":-1, "sx":1 ,  "sy":9 ,  "dx":1 ,  "dy":1 ,  "num_bytes":4096  ,  "type":"READ"                , "timestamp":4350117285464   , "kernel_start_delta":341    }
,{ "proc":"BRISC", "noc":"NOC_1", "vc":-1, "sx":1 ,  "sy":9 ,  "dx":-1,  "dy":-1,  "num_bytes":0     ,  "type":"READ_BARRIER_START"  , "timestamp":4350117285581   , "kernel_start_delta":458    }
,{ "proc":"BRISC", "noc":"NOC_1", "vc":-1, "sx":1 ,  "sy":9 ,  "dx":-1,  "dy":-1,  "num_bytes":0     ,  "type":"READ_BARRIER_END"    , "timestamp":4350117287182   , "kernel_start_delta":2059   }

,{ "proc":"NCRISC", "zone":"NCRISC-KERNEL", "zone_phase":"begin", "sx":1 , "sy":9 , "timestamp" : 4350117285269 }
,{ "proc":"NCRISC", "noc":"NOC_0", "vc":-1, "sx":1 ,  "sy":9 ,  "dx":1 ,  "dy":1 ,  "num_bytes":4096  ,  "type":"READ"                , "timestamp":4350117285492   , "kernel_start_delta":223    }
,{ "proc":"NCRISC", "noc":"NOC_0", "vc":-1, "sx":1 ,  "sy":9 ,  "dx":1 ,  "dy":1 ,  "num_bytes":4096  ,  "type":"READ"                , "timestamp":4350117285634   , "kernel_start_delta":365    }
,{ "proc":"NCRISC", "noc":"NOC_0", "vc":-1, "sx":1 ,  "sy":9 ,  "dx":-1,  "dy":-1,  "num_bytes":0     ,  "type":"READ_BARRIER_START"  , "timestamp":4350117285759   , "kernel_start_delta":490    }
,{ "proc":"NCRISC", "noc":"NOC_0", "vc":-1, "sx":1 ,  "sy":9 ,  "dx":-1,  "dy":-1,  "num_bytes":0     ,  "type":"READ_BARRIER_END"    , "timestamp":4350117287178   , "kernel_start_delta":1909   }

,{ "proc":"BRISC" , "zone":"BRISC-KERNEL", "zone_phase":"begin", "sx":2 , "sy":1 , "timestamp" : 4350117285187 }
,{ "proc":"BRISC", "noc":"NOC_1", "vc":-1, "sx":2 ,  "sy":1 ,  "dx":2 ,  "dy":1 ,  "num_bytes":4096  ,  "type":"READ"                , "timestamp":4350117285377   , "kernel_start_delta":190    }
,{ "proc":"BRISC", "noc":"NOC_1", "vc":-1, "sx":2 ,  "sy":1 ,  "dx":2 ,  "dy":1 ,  "num_bytes":4096  ,  "type":"READ"                , "timestamp":4350117285529   , "kernel_start_delta":342    }
,{ "proc":"BRISC", "noc":"NOC_1", "vc":-1, "sx":2 ,  "sy":1 ,  "dx":-1,  "dy":-1,  "num_bytes":0     ,  "type":"READ_BARRIER_START"  , "timestamp":4350117285644   , "kernel_start_delta":457    }
,{ "proc":"BRISC", "noc":"NOC_1", "vc":-1, "sx":2 ,  "sy":1 ,  "dx":-1,  "dy":-1,  "num_bytes":0     ,  "type":"READ_BARRIER_END"    , "timestamp":4350117286398   , "kernel_start_delta":1211   }

,{ "proc":"NCRISC", "zone":"NCRISC-KERNEL", "zone_phase":"begin", "sx":2 , "sy":1 , "timestamp" : 4350117285333 }
,{ "proc":"NCRISC", "noc":"NOC_0", "vc":-1, "sx":2 ,  "sy":1 ,  "dx":2 ,  "dy":1 ,  "num_bytes":4096  ,  "type":"READ"                , "timestamp":4350117285556   , "kernel_start_delta":223    }
,{ "proc":"NCRISC", "noc":"NOC_0", "vc":-1, "sx":2 ,  "sy":1 ,  "dx":2 ,  "dy":1 ,  "num_bytes":4096  ,  "type":"READ"                , "timestamp":4350117285698   , "kernel_start_delta":365    }
,{ "proc":"NCRISC", "noc":"NOC_0", "vc":-1, "sx":2 ,  "sy":1 ,  "dx":-1,  "dy":-1,  "num_bytes":0     ,  "type":"READ_BARRIER_START"  , "timestamp":4350117285826   , "kernel_start_delta":493    }
,{ "proc":"NCRISC", "noc":"NOC_0", "vc":-1, "sx":2 ,  "sy":1 ,  "dx":-1,  "dy":-1,  "num_bytes":0     ,  "type":"READ_BARRIER_END"    , "timestamp":4350117286560   , "kernel_start_delta":1227   }

,{ "proc":"BRISC" , "zone":"BRISC-KERNEL", "zone_phase":"begin", "sx":2 , "sy":2 , "timestamp" : 4350117285176 }
,{ "proc":"BRISC", "noc":"NOC_1", "vc":-1, "sx":2 ,  "sy":2 ,  "dx":2 ,  "dy":1 ,  "num_bytes":4096  ,  "type":"READ"                , "timestamp":4350117285366   , "kernel_start_delta":190    }
,{ "proc":"BRISC", "noc":"NOC_1", "vc":-1, "sx":2 ,  "sy":2 ,  "dx":2 ,  "dy":1 ,  "num_bytes":4096  ,  "type":"READ"                , "timestamp":4350117285517   , "kernel_start_delta":341    }
,{ "proc":"BRISC", "noc":"NOC_1", "vc":-1, "sx":2 ,  "sy":2 ,  "dx":-1,  "dy":-1,  "num_bytes":0     ,  "type":"READ_BARRIER_START"  , "timestamp":4350117285634   , "kernel_start_delta":458    }
,{ "proc":"BRISC", "noc":"NOC_1", "vc":-1, "sx":2 ,  "sy":2 ,  "dx":-1,  "dy":-1,  "num_bytes":0     ,  "type":"READ_BARRIER_END"    , "timestamp":4350117287667   , "kernel_start_delta":2491   }

,{ "proc":"NCRISC", "zone":"NCRISC-KERNEL", "zone_phase":"begin", "sx":2 , "sy":2 , "timestamp" : 4350117285322 }
,{ "proc":"NCRISC", "noc":"NOC_0", "vc":-1, "sx":2 ,  "sy":2 ,  "dx":2 ,  "dy":1 ,  "num_bytes":4096  ,  "type":"READ"                , "timestamp":4350117285545   , "kernel_start_delta":223    }
,{ "proc":"NCRISC", "noc":"NOC_0", "vc":-1, "sx":2 ,  "sy":2 ,  "dx":2 ,  "dy":1 ,  "num_bytes":4096  ,  "type":"READ"                , "timestamp":4350117285687   , "kernel_start_delta":365    }
,{ "proc":"NCRISC", "noc":"NOC_0", "vc":-1, "sx":2 ,  "sy":2 ,  "dx":-1,  "dy":-1,  "num_bytes":0     ,  "type":"READ_BARRIER_START"  , "timestamp":4350117285812   , "kernel_start_delta":490    }
,{ "proc":"NCRISC", "noc":"NOC_0", "vc":-1, "sx":2 ,  "sy":2 ,  "dx":-1,  "dy":-1,  "num_bytes":0     ,  "type":"READ_BARRIER_END"    , "timestamp":4350117287994   , "kernel_start_delta":2672   }

,{ "proc":"BRISC" , "zone":"BRISC-KERNEL", "zone_phase":"begin", "sx":2 , "sy":3 , "timestamp" : 4350117285165 }
,{ "proc":"BRISC", "noc":"NOC_1", "vc":-1, "sx":2 ,  "sy":3 ,  "dx":2 ,  "dy":1 ,  "num_bytes":4096  ,  "type":"READ"                , "timestamp":4350117285353   , "kernel_start_delta":188    }
,{ "proc":"BRISC", "noc":"NOC_1", "vc":-1, "sx":2 ,  "sy":3 ,  "dx":2 ,  "dy":1 ,  "num_bytes":4096  ,  "type":"READ"                , "timestamp":4350117285507   , "kernel_start_delta":342    }
,{ "proc":"BRISC", "noc":"NOC_1", "vc":-1, "sx":2 ,  "sy":3 ,  "dx":-1,  "dy":-1,  "num_bytes":0     ,  "type":"READ_BARRIER_START"  , "timestamp":4350117285622   , "kernel_start_delta":457    }
,{ "proc":"BRISC", "noc":"NOC_1", "vc":-1, "sx":2 ,  "sy":3 ,  "dx":-1,  "dy":-1,  "num_bytes":0     ,  "type":"READ_BARRIER_END"    , "timestamp":4350117287814   , "kernel_start_delta":2649   }

,{ "proc":"NCRISC", "zone":"NCRISC-KERNEL", "zone_phase":"begin", "sx":2 , "sy":3 , "timestamp" : 4350117285308 }
,{ "proc":"NCRISC", "noc":"NOC_0", "vc":-1, "sx":2 ,  "sy":3 ,  "dx":2 ,  "dy":1 ,  "num_bytes":4096  ,  "type":"READ"                , "timestamp":4350117285532   , "kernel_start_delta":224    }
,{ "proc":"NCRISC", "noc":"NOC_0", "vc":-1, "sx":2 ,  "sy":3 ,  "dx":2 ,  "dy":1 ,  "num_bytes":4096  ,  "type":"READ"                , "timestamp":4350117285674   , "kernel_start_delta":366    }
,{ "proc":"NCRISC", "noc":"NOC_0", "vc":-1, "sx":2 ,  "sy":3 ,  "dx":-1,  "dy":-1,  "num_bytes":0     ,  "type":"READ_BARRIER_START"  , "timestamp":4350117285799   , "kernel_start_delta":491    }
,{ "proc":"NCRISC", "noc":"NOC_0", "vc":-1, "sx":2 ,  "sy":3 ,  "dx":-1,  "dy":-1,  "num_bytes":0     ,  "type":"READ_BARRIER_END"    , "timestamp":4350117287863   , "kernel_start_delta":2555   }

,{ "proc":"BRISC" , "zone":"BRISC-KERNEL", "zone_phase":"begin", "sx":2 , "sy":4 , "timestamp" : 4350117285144 }
,{ "proc":"BRISC", "noc":"NOC_1", "vc":-1, "sx":2 ,  "sy":4 ,  "dx":2 ,  "dy":1 ,  "num_bytes":4096  ,  "type":"READ"                , "timestamp":4350117285332   , "kernel_start_delta":188    }
,{ "proc":"BRISC", "noc":"NOC_1", "vc":-1, "sx":2 ,  "sy":4 ,  "dx":2 ,  "dy":1 ,  "num_bytes":4096  ,  "type":"READ"                , "timestamp":4350117285485   , "kernel_start_delta":341    }
,{ "proc":"BRISC", "noc":"NOC_1", "vc":-1, "sx":2 ,  "sy":4 ,  "dx":-1,  "dy":-1,  "num_bytes":0     ,  "type":"READ_BARRIER_START"  , "timestamp":4350117285602   , "kernel_start_delta":458    }
,{ "proc":"BRISC", "noc":"NOC_1", "vc":-1, "sx":2 ,  "sy":4 ,  "dx":-1,  "dy":-1,  "num_bytes":0     ,  "type":"READ_BARRIER_END"    , "timestamp":4350117287057   , "kernel_start_delta":1913   }

,{ "proc":"NCRISC", "zone":"NCRISC-KERNEL", "zone_phase":"begin", "sx":2 , "sy":4 , "timestamp" : 4350117285288 }
,{ "proc":"NCRISC", "noc":"NOC_0", "vc":-1, "sx":2 ,  "sy":4 ,  "dx":2 ,  "dy":1 ,  "num_bytes":4096  ,  "type":"READ"                , "timestamp":4350117285511   , "kernel_start_delta":223    }
,{ "proc":"NCRISC", "noc":"NOC_0", "vc":-1, "sx":2 ,  "sy":4 ,  "dx":2 ,  "dy":1 ,  "num_bytes":4096  ,  "type":"READ"                , "timestamp":4350117285653   , "kernel_start_delta":365    }
,{ "proc":"NCRISC", "noc":"NOC_0", "vc":-1, "sx":2 ,  "sy":4 ,  "dx":-1,  "dy":-1,  "num_bytes":0     ,  "type":"READ_BARRIER_START"  , "timestamp":4350117285778   , "kernel_start_delta":490    }
,{ "proc":"NCRISC", "noc":"NOC_0", "vc":-1, "sx":2 ,  "sy":4 ,  "dx":-1,  "dy":-1,  "num_bytes":0     ,  "type":"READ_BARRIER_END"    , "timestamp":4350117287719   , "kernel_start_delta":2431   }

,{ "proc":"BRISC" , "zone":"BRISC-KERNEL", "zone_phase":"begin", "sx":2 , "sy":5 , "timestamp" : 4350117285139 }
,{ "proc":"BRISC", "noc":"NOC_1", "vc":-1, "sx":2 ,  "sy":5 ,  "dx":2 ,  "dy":1 ,  "num_bytes":4096  ,  "type":"READ"                , "timestamp":4350117285329   , "kernel_start_delta":190    }
,{ "proc":"BRISC", "noc":"NOC_1", "vc":-1, "sx":2 ,  "sy":5 ,  "dx":2 ,  "dy":1 ,  "num_bytes":4096  ,  "type":"READ"                , "timestamp":4350117285480   , "kernel_start_delta":341    }
,{ "proc":"BRISC", "noc":"NOC_1", "vc":-1, "sx":2 ,  "sy":5 ,  "dx":-1,  "dy":-1,  "num_bytes":0     ,  "type":"READ_BARRIER_START"  , "timestamp":4350117285595   , "kernel_start_delta":456    }
,{ "proc":"BRISC", "noc":"NOC_1", "vc":-1, "sx":2 ,  "sy":5 ,  "dx":-1,  "dy":-1,  "num_bytes":0     ,  "type":"READ_BARRIER_END"    , "timestamp":4350117287345   , "kernel_start_delta":2206   }

,{ "proc":"NCRISC", "zone":"NCRISC-KERNEL", "zone_phase":"begin", "sx":2 , "sy":5 , "timestamp" : 4350117285285 }
,{ "proc":"NCRISC", "noc":"NOC_0", "vc":-1, "sx":2 ,  "sy":5 ,  "dx":2 ,  "dy":1 ,  "num_bytes":4096  ,  "type":"READ"                , "timestamp":4350117285508   , "kernel_start_delta":223    }
,{ "proc":"NCRISC", "noc":"NOC_0", "vc":-1, "sx":2 ,  "sy":5 ,  "dx":2 ,  "dy":1 ,  "num_bytes":4096  ,  "type":"READ"                , "timestamp":4350117285650   , "kernel_start_delta":365    }
,{ "proc":"NCRISC", "noc":"NOC_0", "vc":-1, "sx":2 ,  "sy":5 ,  "dx":-1,  "dy":-1,  "num_bytes":0     ,  "type":"READ_BARRIER_START"  , "timestamp":4350117285778   , "kernel_start_delta":493    }
,{ "proc":"NCRISC", "noc":"NOC_0", "vc":-1, "sx":2 ,  "sy":5 ,  "dx":-1,  "dy":-1,  "num_bytes":0     ,  "type":"READ_BARRIER_END"    , "timestamp":4350117287592   , "kernel_start_delta":2307   }

,{ "proc":"BRISC" , "zone":"BRISC-KERNEL", "zone_phase":"begin", "sx":2 , "sy":7 , "timestamp" : 4350117285119 }
,{ "proc":"BRISC", "noc":"NOC_1", "vc":-1, "sx":2 ,  "sy":7 ,  "dx":2 ,  "dy":1 ,  "num_bytes":4096  ,  "type":"READ"                , "timestamp":4350117285307   , "kernel_start_delta":188    }
,{ "proc":"BRISC", "noc":"NOC_1", "vc":-1, "sx":2 ,  "sy":7 ,  "dx":2 ,  "dy":1 ,  "num_bytes":4096  ,  "type":"READ"                , "timestamp":4350117285460   , "kernel_start_delta":341    }
,{ "proc":"BRISC", "noc":"NOC_1", "vc":-1, "sx":2 ,  "sy":7 ,  "dx":-1,  "dy":-1,  "num_bytes":0     ,  "type":"READ_BARRIER_START"  , "timestamp":4350117285575   , "kernel_start_delta":456    }
,{ "proc":"BRISC", "noc":"NOC_1", "vc":-1, "sx":2 ,  "sy":7 ,  "dx":-1,  "dy":-1,  "num_bytes":0     ,  "type":"READ_BARRIER_END"    , "timestamp":4350117287176   , "kernel_start_delta":2057   }

,{ "proc":"NCRISC", "zone":"NCRISC-KERNEL", "zone_phase":"begin", "sx":2 , "sy":7 , "timestamp" : 4350117285263 }
,{ "proc":"NCRISC", "noc":"NOC_0", "vc":-1, "sx":2 ,  "sy":7 ,  "dx":2 ,  "dy":1 ,  "num_bytes":4096  ,  "type":"READ"                , "timestamp":4350117285486   , "kernel_start_delta":223    }
,{ "proc":"NCRISC", "noc":"NOC_0", "vc":-1, "sx":2 ,  "sy":7 ,  "dx":2 ,  "dy":1 ,  "num_bytes":4096  ,  "type":"READ"                , "timestamp":4350117285628   , "kernel_start_delta":365    }
,{ "proc":"NCRISC", "noc":"NOC_0", "vc":-1, "sx":2 ,  "sy":7 ,  "dx":-1,  "dy":-1,  "num_bytes":0     ,  "type":"READ_BARRIER_START"  , "timestamp":4350117285756   , "kernel_start_delta":493    }
,{ "proc":"NCRISC", "noc":"NOC_0", "vc":-1, "sx":2 ,  "sy":7 ,  "dx":-1,  "dy":-1,  "num_bytes":0     ,  "type":"READ_BARRIER_END"    , "timestamp":4350117287463   , "kernel_start_delta":2200   }

,{ "proc":"BRISC" , "zone":"BRISC-KERNEL", "zone_phase":"begin", "sx":2 , "sy":8 , "timestamp" : 4350117285118 }
,{ "proc":"BRISC", "noc":"NOC_1", "vc":-1, "sx":2 ,  "sy":8 ,  "dx":2 ,  "dy":1 ,  "num_bytes":4096  ,  "type":"READ"                , "timestamp":4350117285306   , "kernel_start_delta":188    }
,{ "proc":"BRISC", "noc":"NOC_1", "vc":-1, "sx":2 ,  "sy":8 ,  "dx":2 ,  "dy":1 ,  "num_bytes":4096  ,  "type":"READ"                , "timestamp":4350117285459   , "kernel_start_delta":341    }
,{ "proc":"BRISC", "noc":"NOC_1", "vc":-1, "sx":2 ,  "sy":8 ,  "dx":-1,  "dy":-1,  "num_bytes":0     ,  "type":"READ_BARRIER_START"  , "timestamp":4350117285576   , "kernel_start_delta":458    }
,{ "proc":"BRISC", "noc":"NOC_1", "vc":-1, "sx":2 ,  "sy":8 ,  "dx":-1,  "dy":-1,  "num_bytes":0     ,  "type":"READ_BARRIER_END"    , "timestamp":4350117287466   , "kernel_start_delta":2348   }

,{ "proc":"NCRISC", "zone":"NCRISC-KERNEL", "zone_phase":"begin", "sx":2 , "sy":8 , "timestamp" : 4350117285262 }
,{ "proc":"NCRISC", "noc":"NOC_0", "vc":-1, "sx":2 ,  "sy":8 ,  "dx":2 ,  "dy":1 ,  "num_bytes":4096  ,  "type":"READ"                , "timestamp":4350117285485   , "kernel_start_delta":223    }
,{ "proc":"NCRISC", "noc":"NOC_0", "vc":-1, "sx":2 ,  "sy":8 ,  "dx":2 ,  "dy":1 ,  "num_bytes":4096  ,  "type":"READ"                , "timestamp":4350117285627   , "kernel_start_delta":365    }
,{ "proc":"NCRISC", "noc":"NOC_0", "vc":-1, "sx":2 ,  "sy":8 ,  "dx":-1,  "dy":-1,  "num_bytes":0     ,  "type":"READ_BARRIER_START"  , "timestamp":4350117285755   , "kernel_start_delta":493    }
,{ "proc":"NCRISC", "noc":"NOC_0", "vc":-1, "sx":2 ,  "sy":8 ,  "dx":-1,  "dy":-1,  "num_bytes":0     ,  "type":"READ_BARRIER_END"    , "timestamp":4350117287326   , "kernel_start_delta":2064   }

,{ "proc":"BRISC" , "zone":"BRISC-KERNEL", "zone_phase":"begin", "sx":2 , "sy":9 , "timestamp" : 4350117285120 }
,{ "proc":"BRISC", "noc":"NOC_1", "vc":-1, "sx":2 ,  "sy":9 ,  "dx":2 ,  "dy":1 ,  "num_bytes":4096  ,  "type":"READ"                , "timestamp":4350117285310   , "kernel_start_delta":190    }
,{ "proc":"BRISC", "noc":"NOC_1", "vc":-1, "sx":2 ,  "sy":9 ,  "dx":2 ,  "dy":1 ,  "num_bytes":4096  ,  "type":"READ"                , "timestamp":4350117285461   , "kernel_start_delta":341    }
,{ "proc":"BRISC", "noc":"NOC_1", "vc":-1, "sx":2 ,  "sy":9 ,  "dx":-1,  "dy":-1,  "num_bytes":0     ,  "type":"READ_BARRIER_START"  , "timestamp":4350117285578   , "kernel_start_delta":458    }
,{ "proc":"BRISC", "noc":"NOC_1", "vc":-1, "sx":2 ,  "sy":9 ,  "dx":-1,  "dy":-1,  "num_bytes":0     ,  "type":"READ_BARRIER_END"    , "timestamp":4350117287902   , "kernel_start_delta":2782   }

,{ "proc":"NCRISC", "zone":"NCRISC-KERNEL", "zone_phase":"begin", "sx":2 , "sy":9 , "timestamp" : 4350117285266 }
,{ "proc":"NCRISC", "noc":"NOC_0", "vc":-1, "sx":2 ,  "sy":9 ,  "dx":2 ,  "dy":1 ,  "num_bytes":4096  ,  "type":"READ"                , "timestamp":4350117285489   , "kernel_start_delta":223    }
,{ "proc":"NCRISC", "noc":"NOC_0", "vc":-1, "sx":2 ,  "sy":9 ,  "dx":2 ,  "dy":1 ,  "num_bytes":4096  ,  "type":"READ"                , "timestamp":4350117285631   , "kernel_start_delta":365    }
,{ "proc":"NCRISC", "noc":"NOC_0", "vc":-1, "sx":2 ,  "sy":9 ,  "dx":-1,  "dy":-1,  "num_bytes":0     ,  "type":"READ_BARRIER_START"  , "timestamp":4350117285759   , "kernel_start_delta":493    }
,{ "proc":"NCRISC", "noc":"NOC_0", "vc":-1, "sx":2 ,  "sy":9 ,  "dx":-1,  "dy":-1,  "num_bytes":0     ,  "type":"READ_BARRIER_END"    , "timestamp":4350117287194   , "kernel_start_delta":1928   }

,{ "proc":"BRISC" , "zone":"BRISC-KERNEL", "zone_phase":"begin", "sx":3 , "sy":1 , "timestamp" : 4350117285262 }
,{ "proc":"BRISC", "noc":"NOC_1", "vc":-1, "sx":3 ,  "sy":1 ,  "dx":3 ,  "dy":1 ,  "num_bytes":4096  ,  "type":"READ"                , "timestamp":4350117285452   , "kernel_start_delta":190    }
,{ "proc":"BRISC", "noc":"NOC_1", "vc":-1, "sx":3 ,  "sy":1 ,  "dx":3 ,  "dy":1 ,  "num_bytes":4096  ,  "type":"READ"                , "timestamp":4350117285604   , "kernel_start_delta":342    }
,{ "proc":"BRISC", "noc":"NOC_1", "vc":-1, "sx":3 ,  "sy":1 ,  "dx":-1,  "dy":-1,  "num_bytes":0     ,  "type":"READ_BARRIER_START"  , "timestamp":4350117285719   , "kernel_start_delta":457    }
,{ "proc":"BRISC", "noc":"NOC_1", "vc":-1, "sx":3 ,  "sy":1 ,  "dx":-1,  "dy":-1,  "num_bytes":0     ,  "type":"READ_BARRIER_END"    , "timestamp":4350117286623   , "kernel_start_delta":1361   }

,{ "proc":"NCRISC", "zone":"NCRISC-KERNEL", "zone_phase":"begin", "sx":3 , "sy":1 , "timestamp" : 4350117285408 }
,{ "proc":"NCRISC", "noc":"NOC_0", "vc":-1, "sx":3 ,  "sy":1 ,  "dx":3 ,  "dy":1 ,  "num_bytes":4096  ,  "type":"READ"                , "timestamp":4350117285633   , "kernel_start_delta":225    }
,{ "proc":"NCRISC", "noc":"NOC_0", "vc":-1, "sx":3 ,  "sy":1 ,  "dx":3 ,  "dy":1 ,  "num_bytes":4096  ,  "type":"READ"                , "timestamp":4350117285776   , "kernel_start_delta":368    }
,{ "proc":"NCRISC", "noc":"NOC_0", "vc":-1, "sx":3 ,  "sy":1 ,  "dx":-1,  "dy":-1,  "num_bytes":0     ,  "type":"READ_BARRIER_START"  , "timestamp":4350117285904   , "kernel_start_delta":496    }
,{ "proc":"NCRISC", "noc":"NOC_0", "vc":-1, "sx":3 ,  "sy":1 ,  "dx":-1,  "dy":-1,  "num_bytes":0     ,  "type":"READ_BARRIER_END"    , "timestamp":4350117286628   , "kernel_start_delta":1220   }

,{ "proc":"BRISC" , "zone":"BRISC-KERNEL", "zone_phase":"begin", "sx":3 , "sy":2 , "timestamp" : 4350117285260 }
,{ "proc":"BRISC", "noc":"NOC_1", "vc":-1, "sx":3 ,  "sy":2 ,  "dx":3 ,  "dy":1 ,  "num_bytes":4096  ,  "type":"READ"                , "timestamp":4350117285448   , "kernel_start_delta":188    }
,{ "proc":"BRISC", "noc":"NOC_1", "vc":-1, "sx":3 ,  "sy":2 ,  "dx":3 ,  "dy":1 ,  "num_bytes":4096  ,  "type":"READ"                , "timestamp":4350117285602   , "kernel_start_delta":342    }
,{ "proc":"BRISC", "noc":"NOC_1", "vc":-1, "sx":3 ,  "sy":2 ,  "dx":-1,  "dy":-1,  "num_bytes":0     ,  "type":"READ_BARRIER_START"  , "timestamp":4350117285717   , "kernel_start_delta":457    }
,{ "proc":"BRISC", "noc":"NOC_1", "vc":-1, "sx":3 ,  "sy":2 ,  "dx":-1,  "dy":-1,  "num_bytes":0     ,  "type":"READ_BARRIER_END"    , "timestamp":4350117287764   , "kernel_start_delta":2504   }

,{ "proc":"NCRISC", "zone":"NCRISC-KERNEL", "zone_phase":"begin", "sx":3 , "sy":2 , "timestamp" : 4350117285403 }
,{ "proc":"NCRISC", "noc":"NOC_0", "vc":-1, "sx":3 ,  "sy":2 ,  "dx":3 ,  "dy":1 ,  "num_bytes":4096  ,  "type":"READ"                , "timestamp":4350117285627   , "kernel_start_delta":224    }
,{ "proc":"NCRISC", "noc":"NOC_0", "vc":-1, "sx":3 ,  "sy":2 ,  "dx":3 ,  "dy":1 ,  "num_bytes":4096  ,  "type":"READ"                , "timestamp":4350117285769   , "kernel_start_delta":366    }
,{ "proc":"NCRISC", "noc":"NOC_0", "vc":-1, "sx":3 ,  "sy":2 ,  "dx":-1,  "dy":-1,  "num_bytes":0     ,  "type":"READ_BARRIER_START"  , "timestamp":4350117285896   , "kernel_start_delta":493    }
,{ "proc":"NCRISC", "noc":"NOC_0", "vc":-1, "sx":3 ,  "sy":2 ,  "dx":-1,  "dy":-1,  "num_bytes":0     ,  "type":"READ_BARRIER_END"    , "timestamp":4350117288083   , "kernel_start_delta":2680   }

,{ "proc":"BRISC" , "zone":"BRISC-KERNEL", "zone_phase":"begin", "sx":3 , "sy":3 , "timestamp" : 4350117285238 }
,{ "proc":"BRISC", "noc":"NOC_1", "vc":-1, "sx":3 ,  "sy":3 ,  "dx":3 ,  "dy":1 ,  "num_bytes":4096  ,  "type":"READ"                , "timestamp":4350117285426   , "kernel_start_delta":188    }
,{ "proc":"BRISC", "noc":"NOC_1", "vc":-1, "sx":3 ,  "sy":3 ,  "dx":3 ,  "dy":1 ,  "num_bytes":4096  ,  "type":"READ"                , "timestamp":4350117285580   , "kernel_start_delta":342    }
,{ "proc":"BRISC", "noc":"NOC_1", "vc":-1, "sx":3 ,  "sy":3 ,  "dx":-1,  "dy":-1,  "num_bytes":0     ,  "type":"READ_BARRIER_START"  , "timestamp":4350117285697   , "kernel_start_delta":459    }
,{ "proc":"BRISC", "noc":"NOC_1", "vc":-1, "sx":3 ,  "sy":3 ,  "dx":-1,  "dy":-1,  "num_bytes":0     ,  "type":"READ_BARRIER_END"    , "timestamp":4350117287455   , "kernel_start_delta":2217   }

,{ "proc":"NCRISC", "zone":"NCRISC-KERNEL", "zone_phase":"begin", "sx":3 , "sy":3 , "timestamp" : 4350117285381 }
,{ "proc":"NCRISC", "noc":"NOC_0", "vc":-1, "sx":3 ,  "sy":3 ,  "dx":3 ,  "dy":1 ,  "num_bytes":4096  ,  "type":"READ"                , "timestamp":4350117285605   , "kernel_start_delta":224    }
,{ "proc":"NCRISC", "noc":"NOC_0", "vc":-1, "sx":3 ,  "sy":3 ,  "dx":3 ,  "dy":1 ,  "num_bytes":4096  ,  "type":"READ"                , "timestamp":4350117285747   , "kernel_start_delta":366    }
,{ "proc":"NCRISC", "noc":"NOC_0", "vc":-1, "sx":3 ,  "sy":3 ,  "dx":-1,  "dy":-1,  "num_bytes":0     ,  "type":"READ_BARRIER_START"  , "timestamp":4350117285872   , "kernel_start_delta":491    }
,{ "proc":"NCRISC", "noc":"NOC_0", "vc":-1, "sx":3 ,  "sy":3 ,  "dx":-1,  "dy":-1,  "num_bytes":0     ,  "type":"READ_BARRIER_END"    , "timestamp":4350117287949   , "kernel_start_delta":2568   }

,{ "proc":"BRISC" , "zone":"BRISC-KERNEL", "zone_phase":"begin", "sx":3 , "sy":4 , "timestamp" : 4350117285206 }
,{ "proc":"BRISC", "noc":"NOC_1", "vc":-1, "sx":3 ,  "sy":4 ,  "dx":3 ,  "dy":1 ,  "num_bytes":4096  ,  "type":"READ"                , "timestamp":4350117285400   , "kernel_start_delta":194    }
,{ "proc":"BRISC", "noc":"NOC_1", "vc":-1, "sx":3 ,  "sy":4 ,  "dx":3 ,  "dy":1 ,  "num_bytes":4096  ,  "type":"READ"                , "timestamp":4350117285553   , "kernel_start_delta":347    }
,{ "proc":"BRISC", "noc":"NOC_1", "vc":-1, "sx":3 ,  "sy":4 ,  "dx":-1,  "dy":-1,  "num_bytes":0     ,  "type":"READ_BARRIER_START"  , "timestamp":4350117285668   , "kernel_start_delta":462    }
,{ "proc":"BRISC", "noc":"NOC_1", "vc":-1, "sx":3 ,  "sy":4 ,  "dx":-1,  "dy":-1,  "num_bytes":0     ,  "type":"READ_BARRIER_END"    , "timestamp":4350117287159   , "kernel_start_delta":1953   }

,{ "proc":"NCRISC", "zone":"NCRISC-KERNEL", "zone_phase":"begin", "sx":3 , "sy":4 , "timestamp" : 4350117285363 }
,{ "proc":"NCRISC", "noc":"NOC_0", "vc":-1, "sx":3 ,  "sy":4 ,  "dx":3 ,  "dy":1 ,  "num_bytes":4096  ,  "type":"READ"                , "timestamp":4350117285589   , "kernel_start_delta":226    }
,{ "proc":"NCRISC", "noc":"NOC_0", "vc":-1, "sx":3 ,  "sy":4 ,  "dx":3 ,  "dy":1 ,  "num_bytes":4096  ,  "type":"READ"                , "timestamp":4350117285731   , "kernel_start_delta":368    }
,{ "proc":"NCRISC", "noc":"NOC_0", "vc":-1, "sx":3 ,  "sy":4 ,  "dx":-1,  "dy":-1,  "num_bytes":0     ,  "type":"READ_BARRIER_START"  , "timestamp":4350117285859   , "kernel_start_delta":496    }
,{ "proc":"NCRISC", "noc":"NOC_0", "vc":-1, "sx":3 ,  "sy":4 ,  "dx":-1,  "dy":-1,  "num_bytes":0     ,  "type":"READ_BARRIER_END"    , "timestamp":4350117287670   , "kernel_start_delta":2307   }

,{ "proc":"BRISC" , "zone":"BRISC-KERNEL", "zone_phase":"begin", "sx":3 , "sy":5 , "timestamp" : 4350117285237 }
,{ "proc":"BRISC", "noc":"NOC_1", "vc":-1, "sx":3 ,  "sy":5 ,  "dx":3 ,  "dy":1 ,  "num_bytes":4096  ,  "type":"READ"                , "timestamp":4350117285425   , "kernel_start_delta":188    }
,{ "proc":"BRISC", "noc":"NOC_1", "vc":-1, "sx":3 ,  "sy":5 ,  "dx":3 ,  "dy":1 ,  "num_bytes":4096  ,  "type":"READ"                , "timestamp":4350117285579   , "kernel_start_delta":342    }
,{ "proc":"BRISC", "noc":"NOC_1", "vc":-1, "sx":3 ,  "sy":5 ,  "dx":-1,  "dy":-1,  "num_bytes":0     ,  "type":"READ_BARRIER_START"  , "timestamp":4350117285696   , "kernel_start_delta":459    }
,{ "proc":"BRISC", "noc":"NOC_1", "vc":-1, "sx":3 ,  "sy":5 ,  "dx":-1,  "dy":-1,  "num_bytes":0     ,  "type":"READ_BARRIER_END"    , "timestamp":4350117287880   , "kernel_start_delta":2643   }

,{ "proc":"NCRISC", "zone":"NCRISC-KERNEL", "zone_phase":"begin", "sx":3 , "sy":5 , "timestamp" : 4350117285380 }
,{ "proc":"NCRISC", "noc":"NOC_0", "vc":-1, "sx":3 ,  "sy":5 ,  "dx":3 ,  "dy":1 ,  "num_bytes":4096  ,  "type":"READ"                , "timestamp":4350117285604   , "kernel_start_delta":224    }
,{ "proc":"NCRISC", "noc":"NOC_0", "vc":-1, "sx":3 ,  "sy":5 ,  "dx":3 ,  "dy":1 ,  "num_bytes":4096  ,  "type":"READ"                , "timestamp":4350117285746   , "kernel_start_delta":366    }
,{ "proc":"NCRISC", "noc":"NOC_0", "vc":-1, "sx":3 ,  "sy":5 ,  "dx":-1,  "dy":-1,  "num_bytes":0     ,  "type":"READ_BARRIER_START"  , "timestamp":4350117285873   , "kernel_start_delta":493    }
,{ "proc":"NCRISC", "noc":"NOC_0", "vc":-1, "sx":3 ,  "sy":5 ,  "dx":-1,  "dy":-1,  "num_bytes":0     ,  "type":"READ_BARRIER_END"    , "timestamp":4350117287820   , "kernel_start_delta":2440   }

,{ "proc":"BRISC" , "zone":"BRISC-KERNEL", "zone_phase":"begin", "sx":3 , "sy":7 , "timestamp" : 4350117285202 }
,{ "proc":"BRISC", "noc":"NOC_1", "vc":-1, "sx":3 ,  "sy":7 ,  "dx":3 ,  "dy":1 ,  "num_bytes":4096  ,  "type":"READ"                , "timestamp":4350117285392   , "kernel_start_delta":190    }
,{ "proc":"BRISC", "noc":"NOC_1", "vc":-1, "sx":3 ,  "sy":7 ,  "dx":3 ,  "dy":1 ,  "num_bytes":4096  ,  "type":"READ"                , "timestamp":4350117285543   , "kernel_start_delta":341    }
,{ "proc":"BRISC", "noc":"NOC_1", "vc":-1, "sx":3 ,  "sy":7 ,  "dx":-1,  "dy":-1,  "num_bytes":0     ,  "type":"READ_BARRIER_START"  , "timestamp":4350117285658   , "kernel_start_delta":456    }
,{ "proc":"BRISC", "noc":"NOC_1", "vc":-1, "sx":3 ,  "sy":7 ,  "dx":-1,  "dy":-1,  "num_bytes":0     ,  "type":"READ_BARRIER_END"    , "timestamp":4350117287280   , "kernel_start_delta":2078   }

,{ "proc":"NCRISC", "zone":"NCRISC-KERNEL", "zone_phase":"begin", "sx":3 , "sy":7 , "timestamp" : 4350117285348 }
,{ "proc":"NCRISC", "noc":"NOC_0", "vc":-1, "sx":3 ,  "sy":7 ,  "dx":3 ,  "dy":1 ,  "num_bytes":4096  ,  "type":"READ"                , "timestamp":4350117285571   , "kernel_start_delta":223    }
,{ "proc":"NCRISC", "noc":"NOC_0", "vc":-1, "sx":3 ,  "sy":7 ,  "dx":3 ,  "dy":1 ,  "num_bytes":4096  ,  "type":"READ"                , "timestamp":4350117285713   , "kernel_start_delta":365    }
,{ "proc":"NCRISC", "noc":"NOC_0", "vc":-1, "sx":3 ,  "sy":7 ,  "dx":-1,  "dy":-1,  "num_bytes":0     ,  "type":"READ_BARRIER_START"  , "timestamp":4350117285835   , "kernel_start_delta":487    }
,{ "proc":"NCRISC", "noc":"NOC_0", "vc":-1, "sx":3 ,  "sy":7 ,  "dx":-1,  "dy":-1,  "num_bytes":0     ,  "type":"READ_BARRIER_END"    , "timestamp":4350117287553   , "kernel_start_delta":2205   }

,{ "proc":"BRISC" , "zone":"BRISC-KERNEL", "zone_phase":"begin", "sx":3 , "sy":8 , "timestamp" : 4350117285197 }
,{ "proc":"BRISC", "noc":"NOC_1", "vc":-1, "sx":3 ,  "sy":8 ,  "dx":3 ,  "dy":1 ,  "num_bytes":4096  ,  "type":"READ"                , "timestamp":4350117285387   , "kernel_start_delta":190    }
,{ "proc":"BRISC", "noc":"NOC_1", "vc":-1, "sx":3 ,  "sy":8 ,  "dx":3 ,  "dy":1 ,  "num_bytes":4096  ,  "type":"READ"                , "timestamp":4350117285538   , "kernel_start_delta":341    }
,{ "proc":"BRISC", "noc":"NOC_1", "vc":-1, "sx":3 ,  "sy":8 ,  "dx":-1,  "dy":-1,  "num_bytes":0     ,  "type":"READ_BARRIER_START"  , "timestamp":4350117285653   , "kernel_start_delta":456    }
,{ "proc":"BRISC", "noc":"NOC_1", "vc":-1, "sx":3 ,  "sy":8 ,  "dx":-1,  "dy":-1,  "num_bytes":0     ,  "type":"READ_BARRIER_END"    , "timestamp":4350117287565   , "kernel_start_delta":2368   }

,{ "proc":"NCRISC", "zone":"NCRISC-KERNEL", "zone_phase":"begin", "sx":3 , "sy":8 , "timestamp" : 4350117285343 }
,{ "proc":"NCRISC", "noc":"NOC_0", "vc":-1, "sx":3 ,  "sy":8 ,  "dx":3 ,  "dy":1 ,  "num_bytes":4096  ,  "type":"READ"                , "timestamp":4350117285566   , "kernel_start_delta":223    }
,{ "proc":"NCRISC", "noc":"NOC_0", "vc":-1, "sx":3 ,  "sy":8 ,  "dx":3 ,  "dy":1 ,  "num_bytes":4096  ,  "type":"READ"                , "timestamp":4350117285708   , "kernel_start_delta":365    }
,{ "proc":"NCRISC", "noc":"NOC_0", "vc":-1, "sx":3 ,  "sy":8 ,  "dx":-1,  "dy":-1,  "num_bytes":0     ,  "type":"READ_BARRIER_START"  , "timestamp":4350117285830   , "kernel_start_delta":487    }
,{ "proc":"NCRISC", "noc":"NOC_0", "vc":-1, "sx":3 ,  "sy":8 ,  "dx":-1,  "dy":-1,  "num_bytes":0     ,  "type":"READ_BARRIER_END"    , "timestamp":4350117287417   , "kernel_start_delta":2074   }

,{ "proc":"BRISC" , "zone":"BRISC-KERNEL", "zone_phase":"begin", "sx":3 , "sy":9 , "timestamp" : 4350117285201 }
,{ "proc":"BRISC", "noc":"NOC_1", "vc":-1, "sx":3 ,  "sy":9 ,  "dx":3 ,  "dy":1 ,  "num_bytes":4096  ,  "type":"READ"                , "timestamp":4350117285389   , "kernel_start_delta":188    }
,{ "proc":"BRISC", "noc":"NOC_1", "vc":-1, "sx":3 ,  "sy":9 ,  "dx":3 ,  "dy":1 ,  "num_bytes":4096  ,  "type":"READ"                , "timestamp":4350117285543   , "kernel_start_delta":342    }
,{ "proc":"BRISC", "noc":"NOC_1", "vc":-1, "sx":3 ,  "sy":9 ,  "dx":-1,  "dy":-1,  "num_bytes":0     ,  "type":"READ_BARRIER_START"  , "timestamp":4350117285662   , "kernel_start_delta":461    }
,{ "proc":"BRISC", "noc":"NOC_1", "vc":-1, "sx":3 ,  "sy":9 ,  "dx":-1,  "dy":-1,  "num_bytes":0     ,  "type":"READ_BARRIER_END"    , "timestamp":4350117287991   , "kernel_start_delta":2790   }

,{ "proc":"NCRISC", "zone":"NCRISC-KERNEL", "zone_phase":"begin", "sx":3 , "sy":9 , "timestamp" : 4350117285344 }
,{ "proc":"NCRISC", "noc":"NOC_0", "vc":-1, "sx":3 ,  "sy":9 ,  "dx":3 ,  "dy":1 ,  "num_bytes":4096  ,  "type":"READ"                , "timestamp":4350117285568   , "kernel_start_delta":224    }
,{ "proc":"NCRISC", "noc":"NOC_0", "vc":-1, "sx":3 ,  "sy":9 ,  "dx":3 ,  "dy":1 ,  "num_bytes":4096  ,  "type":"READ"                , "timestamp":4350117285710   , "kernel_start_delta":366    }
,{ "proc":"NCRISC", "noc":"NOC_0", "vc":-1, "sx":3 ,  "sy":9 ,  "dx":-1,  "dy":-1,  "num_bytes":0     ,  "type":"READ_BARRIER_START"  , "timestamp":4350117285835   , "kernel_start_delta":491    }
,{ "proc":"NCRISC", "noc":"NOC_0", "vc":-1, "sx":3 ,  "sy":9 ,  "dx":-1,  "dy":-1,  "num_bytes":0     ,  "type":"READ_BARRIER_END"    , "timestamp":4350117287286   , "kernel_start_delta":1942   }

,{ "proc":"BRISC" , "zone":"BRISC-KERNEL", "zone_phase":"begin", "sx":4 , "sy":1 , "timestamp" : 4350117285246 }
,{ "proc":"BRISC", "noc":"NOC_1", "vc":-1, "sx":4 ,  "sy":1 ,  "dx":4 ,  "dy":1 ,  "num_bytes":4096  ,  "type":"READ"                , "timestamp":4350117285436   , "kernel_start_delta":190    }
,{ "proc":"BRISC", "noc":"NOC_1", "vc":-1, "sx":4 ,  "sy":1 ,  "dx":4 ,  "dy":1 ,  "num_bytes":4096  ,  "type":"READ"                , "timestamp":4350117285587   , "kernel_start_delta":341    }
,{ "proc":"BRISC", "noc":"NOC_1", "vc":-1, "sx":4 ,  "sy":1 ,  "dx":-1,  "dy":-1,  "num_bytes":0     ,  "type":"READ_BARRIER_START"  , "timestamp":4350117285704   , "kernel_start_delta":458    }
,{ "proc":"BRISC", "noc":"NOC_1", "vc":-1, "sx":4 ,  "sy":1 ,  "dx":-1,  "dy":-1,  "num_bytes":0     ,  "type":"READ_BARRIER_END"    , "timestamp":4350117286745   , "kernel_start_delta":1499   }

,{ "proc":"NCRISC", "zone":"NCRISC-KERNEL", "zone_phase":"begin", "sx":4 , "sy":1 , "timestamp" : 4350117285392 }
,{ "proc":"NCRISC", "noc":"NOC_0", "vc":-1, "sx":4 ,  "sy":1 ,  "dx":4 ,  "dy":1 ,  "num_bytes":4096  ,  "type":"READ"                , "timestamp":4350117285615   , "kernel_start_delta":223    }
,{ "proc":"NCRISC", "noc":"NOC_0", "vc":-1, "sx":4 ,  "sy":1 ,  "dx":4 ,  "dy":1 ,  "num_bytes":4096  ,  "type":"READ"                , "timestamp":4350117285757   , "kernel_start_delta":365    }
,{ "proc":"NCRISC", "noc":"NOC_0", "vc":-1, "sx":4 ,  "sy":1 ,  "dx":-1,  "dy":-1,  "num_bytes":0     ,  "type":"READ_BARRIER_START"  , "timestamp":4350117285885   , "kernel_start_delta":493    }
,{ "proc":"NCRISC", "noc":"NOC_0", "vc":-1, "sx":4 ,  "sy":1 ,  "dx":-1,  "dy":-1,  "num_bytes":0     ,  "type":"READ_BARRIER_END"    , "timestamp":4350117286563   , "kernel_start_delta":1171   }

,{ "proc":"BRISC" , "zone":"BRISC-KERNEL", "zone_phase":"begin", "sx":4 , "sy":2 , "timestamp" : 4350117285238 }
,{ "proc":"BRISC", "noc":"NOC_1", "vc":-1, "sx":4 ,  "sy":2 ,  "dx":4 ,  "dy":1 ,  "num_bytes":4096  ,  "type":"READ"                , "timestamp":4350117285428   , "kernel_start_delta":190    }
,{ "proc":"BRISC", "noc":"NOC_1", "vc":-1, "sx":4 ,  "sy":2 ,  "dx":4 ,  "dy":1 ,  "num_bytes":4096  ,  "type":"READ"                , "timestamp":4350117285579   , "kernel_start_delta":341    }
,{ "proc":"BRISC", "noc":"NOC_1", "vc":-1, "sx":4 ,  "sy":2 ,  "dx":-1,  "dy":-1,  "num_bytes":0     ,  "type":"READ_BARRIER_START"  , "timestamp":4350117285694   , "kernel_start_delta":456    }
,{ "proc":"BRISC", "noc":"NOC_1", "vc":-1, "sx":4 ,  "sy":2 ,  "dx":-1,  "dy":-1,  "num_bytes":0     ,  "type":"READ_BARRIER_END"    , "timestamp":4350117287879   , "kernel_start_delta":2641   }

,{ "proc":"NCRISC", "zone":"NCRISC-KERNEL", "zone_phase":"begin", "sx":4 , "sy":2 , "timestamp" : 4350117285384 }
,{ "proc":"NCRISC", "noc":"NOC_0", "vc":-1, "sx":4 ,  "sy":2 ,  "dx":4 ,  "dy":1 ,  "num_bytes":4096  ,  "type":"READ"                , "timestamp":4350117285605   , "kernel_start_delta":221    }
,{ "proc":"NCRISC", "noc":"NOC_0", "vc":-1, "sx":4 ,  "sy":2 ,  "dx":4 ,  "dy":1 ,  "num_bytes":4096  ,  "type":"READ"                , "timestamp":4350117285747   , "kernel_start_delta":363    }
,{ "proc":"NCRISC", "noc":"NOC_0", "vc":-1, "sx":4 ,  "sy":2 ,  "dx":-1,  "dy":-1,  "num_bytes":0     ,  "type":"READ_BARRIER_START"  , "timestamp":4350117285872   , "kernel_start_delta":488    }
,{ "proc":"NCRISC", "noc":"NOC_0", "vc":-1, "sx":4 ,  "sy":2 ,  "dx":-1,  "dy":-1,  "num_bytes":0     ,  "type":"READ_BARRIER_END"    , "timestamp":4350117288013   , "kernel_start_delta":2629   }

,{ "proc":"BRISC" , "zone":"BRISC-KERNEL", "zone_phase":"begin", "sx":4 , "sy":3 , "timestamp" : 4350117285224 }
,{ "proc":"BRISC", "noc":"NOC_1", "vc":-1, "sx":4 ,  "sy":3 ,  "dx":4 ,  "dy":1 ,  "num_bytes":4096  ,  "type":"READ"                , "timestamp":4350117285412   , "kernel_start_delta":188    }
,{ "proc":"BRISC", "noc":"NOC_1", "vc":-1, "sx":4 ,  "sy":3 ,  "dx":4 ,  "dy":1 ,  "num_bytes":4096  ,  "type":"READ"                , "timestamp":4350117285566   , "kernel_start_delta":342    }
,{ "proc":"BRISC", "noc":"NOC_1", "vc":-1, "sx":4 ,  "sy":3 ,  "dx":-1,  "dy":-1,  "num_bytes":0     ,  "type":"READ_BARRIER_START"  , "timestamp":4350117285683   , "kernel_start_delta":459    }
,{ "proc":"BRISC", "noc":"NOC_1", "vc":-1, "sx":4 ,  "sy":3 ,  "dx":-1,  "dy":-1,  "num_bytes":0     ,  "type":"READ_BARRIER_END"    , "timestamp":4350117287577   , "kernel_start_delta":2353   }

,{ "proc":"NCRISC", "zone":"NCRISC-KERNEL", "zone_phase":"begin", "sx":4 , "sy":3 , "timestamp" : 4350117285367 }
,{ "proc":"NCRISC", "noc":"NOC_0", "vc":-1, "sx":4 ,  "sy":3 ,  "dx":4 ,  "dy":1 ,  "num_bytes":4096  ,  "type":"READ"                , "timestamp":4350117285591   , "kernel_start_delta":224    }
,{ "proc":"NCRISC", "noc":"NOC_0", "vc":-1, "sx":4 ,  "sy":3 ,  "dx":4 ,  "dy":1 ,  "num_bytes":4096  ,  "type":"READ"                , "timestamp":4350117285733   , "kernel_start_delta":366    }
,{ "proc":"NCRISC", "noc":"NOC_0", "vc":-1, "sx":4 ,  "sy":3 ,  "dx":-1,  "dy":-1,  "num_bytes":0     ,  "type":"READ_BARRIER_START"  , "timestamp":4350117285858   , "kernel_start_delta":491    }
,{ "proc":"NCRISC", "noc":"NOC_0", "vc":-1, "sx":4 ,  "sy":3 ,  "dx":-1,  "dy":-1,  "num_bytes":0     ,  "type":"READ_BARRIER_END"    , "timestamp":4350117287871   , "kernel_start_delta":2504   }

,{ "proc":"BRISC" , "zone":"BRISC-KERNEL", "zone_phase":"begin", "sx":4 , "sy":4 , "timestamp" : 4350117285184 }
,{ "proc":"BRISC", "noc":"NOC_1", "vc":-1, "sx":4 ,  "sy":4 ,  "dx":4 ,  "dy":1 ,  "num_bytes":4096  ,  "type":"READ"                , "timestamp":4350117285378   , "kernel_start_delta":194    }
,{ "proc":"BRISC", "noc":"NOC_1", "vc":-1, "sx":4 ,  "sy":4 ,  "dx":4 ,  "dy":1 ,  "num_bytes":4096  ,  "type":"READ"                , "timestamp":4350117285531   , "kernel_start_delta":347    }
,{ "proc":"BRISC", "noc":"NOC_1", "vc":-1, "sx":4 ,  "sy":4 ,  "dx":-1,  "dy":-1,  "num_bytes":0     ,  "type":"READ_BARRIER_START"  , "timestamp":4350117285646   , "kernel_start_delta":462    }
,{ "proc":"BRISC", "noc":"NOC_1", "vc":-1, "sx":4 ,  "sy":4 ,  "dx":-1,  "dy":-1,  "num_bytes":0     ,  "type":"READ_BARRIER_END"    , "timestamp":4350117287113   , "kernel_start_delta":1929   }

,{ "proc":"NCRISC", "zone":"NCRISC-KERNEL", "zone_phase":"begin", "sx":4 , "sy":4 , "timestamp" : 4350117285341 }
,{ "proc":"NCRISC", "noc":"NOC_0", "vc":-1, "sx":4 ,  "sy":4 ,  "dx":4 ,  "dy":1 ,  "num_bytes":4096  ,  "type":"READ"                , "timestamp":4350117285567   , "kernel_start_delta":226    }
,{ "proc":"NCRISC", "noc":"NOC_0", "vc":-1, "sx":4 ,  "sy":4 ,  "dx":4 ,  "dy":1 ,  "num_bytes":4096  ,  "type":"READ"                , "timestamp":4350117285709   , "kernel_start_delta":368    }
,{ "proc":"NCRISC", "noc":"NOC_0", "vc":-1, "sx":4 ,  "sy":4 ,  "dx":-1,  "dy":-1,  "num_bytes":0     ,  "type":"READ_BARRIER_START"  , "timestamp":4350117285837   , "kernel_start_delta":496    }
,{ "proc":"NCRISC", "noc":"NOC_0", "vc":-1, "sx":4 ,  "sy":4 ,  "dx":-1,  "dy":-1,  "num_bytes":0     ,  "type":"READ_BARRIER_END"    , "timestamp":4350117287744   , "kernel_start_delta":2403   }

,{ "proc":"BRISC" , "zone":"BRISC-KERNEL", "zone_phase":"begin", "sx":4 , "sy":5 , "timestamp" : 4350117285203 }
,{ "proc":"BRISC", "noc":"NOC_1", "vc":-1, "sx":4 ,  "sy":5 ,  "dx":4 ,  "dy":1 ,  "num_bytes":4096  ,  "type":"READ"                , "timestamp":4350117285393   , "kernel_start_delta":190    }
,{ "proc":"BRISC", "noc":"NOC_1", "vc":-1, "sx":4 ,  "sy":5 ,  "dx":4 ,  "dy":1 ,  "num_bytes":4096  ,  "type":"READ"                , "timestamp":4350117285544   , "kernel_start_delta":341    }
,{ "proc":"BRISC", "noc":"NOC_1", "vc":-1, "sx":4 ,  "sy":5 ,  "dx":-1,  "dy":-1,  "num_bytes":0     ,  "type":"READ_BARRIER_START"  , "timestamp":4350117285661   , "kernel_start_delta":458    }
,{ "proc":"BRISC", "noc":"NOC_1", "vc":-1, "sx":4 ,  "sy":5 ,  "dx":-1,  "dy":-1,  "num_bytes":0     ,  "type":"READ_BARRIER_END"    , "timestamp":4350117287406   , "kernel_start_delta":2203   }

,{ "proc":"NCRISC", "zone":"NCRISC-KERNEL", "zone_phase":"begin", "sx":4 , "sy":5 , "timestamp" : 4350117285349 }
,{ "proc":"NCRISC", "noc":"NOC_0", "vc":-1, "sx":4 ,  "sy":5 ,  "dx":4 ,  "dy":1 ,  "num_bytes":4096  ,  "type":"READ"                , "timestamp":4350117285572   , "kernel_start_delta":223    }
,{ "proc":"NCRISC", "noc":"NOC_0", "vc":-1, "sx":4 ,  "sy":5 ,  "dx":4 ,  "dy":1 ,  "num_bytes":4096  ,  "type":"READ"                , "timestamp":4350117285714   , "kernel_start_delta":365    }
,{ "proc":"NCRISC", "noc":"NOC_0", "vc":-1, "sx":4 ,  "sy":5 ,  "dx":-1,  "dy":-1,  "num_bytes":0     ,  "type":"READ_BARRIER_START"  , "timestamp":4350117285839   , "kernel_start_delta":490    }
,{ "proc":"NCRISC", "noc":"NOC_0", "vc":-1, "sx":4 ,  "sy":5 ,  "dx":-1,  "dy":-1,  "num_bytes":0     ,  "type":"READ_BARRIER_END"    , "timestamp":4350117287604   , "kernel_start_delta":2255   }

,{ "proc":"BRISC" , "zone":"BRISC-KERNEL", "zone_phase":"begin", "sx":4 , "sy":7 , "timestamp" : 4350117285189 }
,{ "proc":"BRISC", "noc":"NOC_1", "vc":-1, "sx":4 ,  "sy":7 ,  "dx":4 ,  "dy":1 ,  "num_bytes":4096  ,  "type":"READ"                , "timestamp":4350117285377   , "kernel_start_delta":188    }
,{ "proc":"BRISC", "noc":"NOC_1", "vc":-1, "sx":4 ,  "sy":7 ,  "dx":4 ,  "dy":1 ,  "num_bytes":4096  ,  "type":"READ"                , "timestamp":4350117285530   , "kernel_start_delta":341    }
,{ "proc":"BRISC", "noc":"NOC_1", "vc":-1, "sx":4 ,  "sy":7 ,  "dx":-1,  "dy":-1,  "num_bytes":0     ,  "type":"READ_BARRIER_START"  , "timestamp":4350117285647   , "kernel_start_delta":458    }
,{ "proc":"BRISC", "noc":"NOC_1", "vc":-1, "sx":4 ,  "sy":7 ,  "dx":-1,  "dy":-1,  "num_bytes":0     ,  "type":"READ_BARRIER_END"    , "timestamp":4350117287695   , "kernel_start_delta":2506   }

,{ "proc":"NCRISC", "zone":"NCRISC-KERNEL", "zone_phase":"begin", "sx":4 , "sy":7 , "timestamp" : 4350117285333 }
,{ "proc":"NCRISC", "noc":"NOC_0", "vc":-1, "sx":4 ,  "sy":7 ,  "dx":4 ,  "dy":1 ,  "num_bytes":4096  ,  "type":"READ"                , "timestamp":4350117285553   , "kernel_start_delta":220    }
,{ "proc":"NCRISC", "noc":"NOC_0", "vc":-1, "sx":4 ,  "sy":7 ,  "dx":4 ,  "dy":1 ,  "num_bytes":4096  ,  "type":"READ"                , "timestamp":4350117285695   , "kernel_start_delta":362    }
,{ "proc":"NCRISC", "noc":"NOC_0", "vc":-1, "sx":4 ,  "sy":7 ,  "dx":-1,  "dy":-1,  "num_bytes":0     ,  "type":"READ_BARRIER_START"  , "timestamp":4350117285823   , "kernel_start_delta":490    }
,{ "proc":"NCRISC", "noc":"NOC_0", "vc":-1, "sx":4 ,  "sy":7 ,  "dx":-1,  "dy":-1,  "num_bytes":0     ,  "type":"READ_BARRIER_END"    , "timestamp":4350117287474   , "kernel_start_delta":2141   }

,{ "proc":"BRISC" , "zone":"BRISC-KERNEL", "zone_phase":"begin", "sx":4 , "sy":8 , "timestamp" : 4350117285190 }
,{ "proc":"BRISC", "noc":"NOC_1", "vc":-1, "sx":4 ,  "sy":8 ,  "dx":4 ,  "dy":1 ,  "num_bytes":4096  ,  "type":"READ"                , "timestamp":4350117285380   , "kernel_start_delta":190    }
,{ "proc":"BRISC", "noc":"NOC_1", "vc":-1, "sx":4 ,  "sy":8 ,  "dx":4 ,  "dy":1 ,  "num_bytes":4096  ,  "type":"READ"                , "timestamp":4350117285533   , "kernel_start_delta":343    }
,{ "proc":"BRISC", "noc":"NOC_1", "vc":-1, "sx":4 ,  "sy":8 ,  "dx":-1,  "dy":-1,  "num_bytes":0     ,  "type":"READ_BARRIER_START"  , "timestamp":4350117285650   , "kernel_start_delta":460    }
,{ "proc":"BRISC", "noc":"NOC_1", "vc":-1, "sx":4 ,  "sy":8 ,  "dx":-1,  "dy":-1,  "num_bytes":0     ,  "type":"READ_BARRIER_END"    , "timestamp":4350117287978   , "kernel_start_delta":2788   }

,{ "proc":"NCRISC", "zone":"NCRISC-KERNEL", "zone_phase":"begin", "sx":4 , "sy":8 , "timestamp" : 4350117285336 }
,{ "proc":"NCRISC", "noc":"NOC_0", "vc":-1, "sx":4 ,  "sy":8 ,  "dx":4 ,  "dy":1 ,  "num_bytes":4096  ,  "type":"READ"                , "timestamp":4350117285559   , "kernel_start_delta":223    }
,{ "proc":"NCRISC", "noc":"NOC_0", "vc":-1, "sx":4 ,  "sy":8 ,  "dx":4 ,  "dy":1 ,  "num_bytes":4096  ,  "type":"READ"                , "timestamp":4350117285701   , "kernel_start_delta":365    }
,{ "proc":"NCRISC", "noc":"NOC_0", "vc":-1, "sx":4 ,  "sy":8 ,  "dx":-1,  "dy":-1,  "num_bytes":0     ,  "type":"READ_BARRIER_START"  , "timestamp":4350117285826   , "kernel_start_delta":490    }
,{ "proc":"NCRISC", "noc":"NOC_0", "vc":-1, "sx":4 ,  "sy":8 ,  "dx":-1,  "dy":-1,  "num_bytes":0     ,  "type":"READ_BARRIER_END"    , "timestamp":4350117287341   , "kernel_start_delta":2005   }

,{ "proc":"BRISC" , "zone":"BRISC-KERNEL", "zone_phase":"begin", "sx":4 , "sy":9 , "timestamp" : 4350117285156 }
,{ "proc":"BRISC", "noc":"NOC_1", "vc":-1, "sx":4 ,  "sy":9 ,  "dx":4 ,  "dy":1 ,  "num_bytes":4096  ,  "type":"READ"                , "timestamp":4350117285344   , "kernel_start_delta":188    }
,{ "proc":"BRISC", "noc":"NOC_1", "vc":-1, "sx":4 ,  "sy":9 ,  "dx":4 ,  "dy":1 ,  "num_bytes":4096  ,  "type":"READ"                , "timestamp":4350117285498   , "kernel_start_delta":342    }
,{ "proc":"BRISC", "noc":"NOC_1", "vc":-1, "sx":4 ,  "sy":9 ,  "dx":-1,  "dy":-1,  "num_bytes":0     ,  "type":"READ_BARRIER_START"  , "timestamp":4350117285613   , "kernel_start_delta":457    }
,{ "proc":"BRISC", "noc":"NOC_1", "vc":-1, "sx":4 ,  "sy":9 ,  "dx":-1,  "dy":-1,  "num_bytes":0     ,  "type":"READ_BARRIER_END"    , "timestamp":4350117287223   , "kernel_start_delta":2067   }

,{ "proc":"NCRISC", "zone":"NCRISC-KERNEL", "zone_phase":"begin", "sx":4 , "sy":9 , "timestamp" : 4350117285299 }
,{ "proc":"NCRISC", "noc":"NOC_0", "vc":-1, "sx":4 ,  "sy":9 ,  "dx":4 ,  "dy":1 ,  "num_bytes":4096  ,  "type":"READ"                , "timestamp":4350117285523   , "kernel_start_delta":224    }
,{ "proc":"NCRISC", "noc":"NOC_0", "vc":-1, "sx":4 ,  "sy":9 ,  "dx":4 ,  "dy":1 ,  "num_bytes":4096  ,  "type":"READ"                , "timestamp":4350117285665   , "kernel_start_delta":366    }
,{ "proc":"NCRISC", "noc":"NOC_0", "vc":-1, "sx":4 ,  "sy":9 ,  "dx":-1,  "dy":-1,  "num_bytes":0     ,  "type":"READ_BARRIER_START"  , "timestamp":4350117285795   , "kernel_start_delta":496    }
,{ "proc":"NCRISC", "noc":"NOC_0", "vc":-1, "sx":4 ,  "sy":9 ,  "dx":-1,  "dy":-1,  "num_bytes":0     ,  "type":"READ_BARRIER_END"    , "timestamp":4350117287070   , "kernel_start_delta":1771   }
]
